gtfs2nx/__init__.py
gtfs2nx/network.py
gtfs2nx/network_backup.py
gtfs2nx/utils.py
gtfs2nx-0.2.1.dist-info/LICENSE
gtfs2nx-0.2.1.dist-info/METADATA
gtfs2nx-0.2.1.dist-info/WHEEL
gtfs2nx-0.2.1.dist-info/RECORD
