Metadata-Version: 2.1
Name: gtfs2nx
Version: 0.2.1
Summary: Convert GTFS feeds to realistic, routable NetworkX graph.
Author: Florian Nachtigall
Author-email: nachtigall@tu-berlin.de
Requires-Python: >=3.10,<4.0
Classifier: Programming Language :: Python :: 3
Classifier: Programming Language :: Python :: 3.10
Classifier: Programming Language :: Python :: 3.11
Requires-Dist: geopandas (>=0.13.2,<0.14.0)
Requires-Dist: matplotlib (>=3.7.2,<4.0.0)
Requires-Dist: networkx (>=3.1,<4.0)
Requires-Dist: numpy (>=1.25.2,<2.0.0)
Requires-Dist: pandas (>=2.0.3,<3.0.0)
Requires-Dist: partridge (==1.1.2)
Requires-Dist: scikit-learn (>=1.3.0,<2.0.0)
